SigProfilerMatrixGenerator/__init__.py
SigProfilerMatrixGenerator/install.py
SigProfilerMatrixGenerator/test_helpers.py
SigProfilerMatrixGenerator/version.py
SigProfilerMatrixGenerator/controllers/__init__.py
SigProfilerMatrixGenerator/controllers/cli_controller.py
SigProfilerMatrixGenerator/references/CNV/.DS_Store
SigProfilerMatrixGenerator/references/CNV/CNV_features.tsv
SigProfilerMatrixGenerator/references/CNV/CN_classes_dictionary.txt
SigProfilerMatrixGenerator/references/CNV/example_input/Battenberg_test.tsv
SigProfilerMatrixGenerator/references/CNV/example_input/all.breast.ascat.summary.sample.tsv
SigProfilerMatrixGenerator/references/CNV/example_output/BATTENBERG-TEST.CNV48.matrix.tsv
SigProfilerMatrixGenerator/references/SV/example_input/560-Breast/PD11346a.560_breast.rearrangements.n560.bedpe
SigProfilerMatrixGenerator/references/SV/example_input/560-Breast/PD11348a.560_breast.rearrangements.n560.bedpe
SigProfilerMatrixGenerator/references/SV/example_input/560-Breast/PD11352a.560_breast.rearrangements.n560.bedpe
SigProfilerMatrixGenerator/references/SV/example_input/560-Breast/PD11361a.560_breast.rearrangements.n560.bedpe
SigProfilerMatrixGenerator/references/SV/example_input/560-Breast/PD11379a.560_breast.rearrangements.n560.bedpe
SigProfilerMatrixGenerator/references/SV/example_input/560-Breast/PD11384a.560_breast.rearrangements.n560.bedpe
SigProfilerMatrixGenerator/references/SV/example_input/560-Breast/PD11389a.560_breast.rearrangements.n560.bedpe
SigProfilerMatrixGenerator/references/SV/example_input/560-Breast/PD11742a.560_breast.rearrangements.n560.bedpe
SigProfilerMatrixGenerator/references/SV/example_input/560-Breast/PD11743a.560_breast.rearrangements.n560.bedpe
SigProfilerMatrixGenerator/references/SV/example_input/560-Breast/PD11748a.560_breast.rearrangements.n560.bedpe
SigProfilerMatrixGenerator/references/SV/example_input/560-Breast/PD13162a.560_breast.rearrangements.n560.bedpe
sigprofilermatrixgenerator-1.3.5.dist-info/licenses/LICENSE
sigprofilermatrixgenerator-1.3.5.dist-info/METADATA
sigprofilermatrixgenerator-1.3.5.dist-info/WHEEL
sigprofilermatrixgenerator-1.3.5.dist-info/entry_points.txt
sigprofilermatrixgenerator-1.3.5.dist-info/top_level.txt
sigprofilermatrixgenerator-1.3.5.dist-info/RECORD
