Metadata-Version: 2.4
Name: SigProfilerMatrixGenerator
Version: 1.3.5
Summary: SigProfiler matrix generator tool
Home-page: https://github.com/AlexandrovLab/SigProfilerMatrixGenerator.git
Author: Erik Bergstrom
Author-email: ebergstr@eng.ucsd.edu
License: UCSD
Requires-Python: >=3.9
License-File: LICENSE
Requires-Dist: matplotlib>=2.2.2
Requires-Dist: sigProfilerPlotting>=1.4.1
Requires-Dist: statsmodels>=0.9.0
Requires-Dist: numpy>=2.0.0
Requires-Dist: pandas>=2.0.0
Requires-Dist: scipy>=1.12.0
Provides-Extra: tests
Requires-Dist: pytest; extra == "tests"
Dynamic: author
Dynamic: author-email
Dynamic: description
Dynamic: description-content-type
Dynamic: home-page
Dynamic: license
Dynamic: license-file
Dynamic: provides-extra
Dynamic: requires-dist
Dynamic: requires-python
Dynamic: summary
